tracktime/__init__.py
tracktime/__main__.py
tracktime/cli.py
tracktime/config.py
tracktime/entry_list.py
tracktime/report.py
tracktime/synchronisers/__init__.py
tracktime/synchronisers/base.py
tracktime/synchronisers/github.py
tracktime/synchronisers/gitlab.py
tracktime/synchronisers/linear.py
tracktime/synchronisers/sourcehut.py
tracktime/time_entry.py
tracktime/time_parser.py
tracktime-0.10.0.dist-info/entry_points.txt
tracktime-0.10.0.dist-info/LICENSE
tracktime-0.10.0.dist-info/WHEEL
tracktime-0.10.0.dist-info/METADATA
tracktime-0.10.0.dist-info/RECORD
