Metadata-Version: 2.1
Name: tracktime
Version: 0.10.0
Summary: Time tracking library with command line interface.
Home-page: https://git.sr.ht/~sumner/tracktime
License: GPL-3.0-or-later
Keywords: time,tracking
Author: Sumner Evans
Author-email: inquiries@sumnerevans.com
Requires-Python: >=3.7,<4.0
Classifier: Development Status :: 4 - Beta
Classifier: Intended Audience :: End Users/Desktop
Classifier: License :: OSI Approved :: GNU General Public License v3 or later (GPLv3+)
Classifier: Operating System :: POSIX
Classifier: Programming Language :: Python :: 3
Classifier: Programming Language :: Python :: 3.7
Classifier: Programming Language :: Python :: 3.8
Classifier: Programming Language :: Python :: 3.9
Requires-Dist: pdfkit (>=0.6.1,<0.7.0)
Requires-Dist: pyyaml (>=5.3.1,<6.0.0)
Requires-Dist: requests (>=2.24.0,<3.0.0)
Requires-Dist: tabulate (>=0.8.7,<0.9.0)
Project-URL: Bug Tracker, https://todo.sr.ht/~sumner/tracktime
Project-URL: Repository, https://git.sr.ht/~sumner/tracktime
